sentry_api/__init__.py
sentry_api/api.py
sentry_api/exceptions.py
sentry_api/http.py
sentry_api/resources/__init__.py
sentry_api/resources/base.py
sentry_api/resources/project_rules.py
sentry_api/resources/projects.py
sentry_api/resources/teams.py
sentry_api_python-0.3.0.dist-info/LICENSE
sentry_api_python-0.3.0.dist-info/METADATA
sentry_api_python-0.3.0.dist-info/WHEEL
sentry_api_python-0.3.0.dist-info/RECORD
