Metadata-Version: 2.1
Name: sentry-api-python
Version: 0.3.0
Summary: SDK in Python to simplify access Sentry API (https://docs.sentry.io/api/)
Home-page: https://github.com/epsylabs/sentry-api-python
License: MIT
Keywords: sentry,sentry-api-sdk
Author: Daniel Ancuta
Author-email: whisller@gmail.com
Requires-Python: >=3.8.1,<4.0.0
Classifier: Development Status :: 3 - Alpha
Classifier: Environment :: Console
Classifier: Environment :: Web Environment
Classifier: Intended Audience :: Developers
Classifier: License :: OSI Approved :: MIT License
Classifier: Operating System :: OS Independent
Classifier: Programming Language :: Python
Classifier: Programming Language :: Python :: 3
Classifier: Programming Language :: Python :: 3.9
Classifier: Programming Language :: Python :: 3.10
Classifier: Programming Language :: Python :: 3.11
Classifier: Programming Language :: Python :: 3
Classifier: Programming Language :: Python :: 3 :: Only
Classifier: Programming Language :: Python :: 3.8
Requires-Dist: requests (>=2.28.2,<3.0.0)
Project-URL: Repository, https://github.com/epsylabs/sentry-api-python
